kblaunch/__init__.py
kblaunch/bash_utils.py
kblaunch/cli.py
kblaunch/plots.py
kblaunch/vscode.sh
kblaunch-0.3.9.dist-info/METADATA
kblaunch-0.3.9.dist-info/WHEEL
kblaunch-0.3.9.dist-info/entry_points.txt
kblaunch-0.3.9.dist-info/licenses/LICENSE
kblaunch-0.3.9.dist-info/RECORD
