Metadata-Version: 2.4
Name: kblaunch
Version: 0.3.9
Summary: A CLI tool for launching Kubernetes job fast in EIDF
Author-email: Gautier Dagan <gautier.dagan@ed.ac.uk>
License-Expression: MIT
License-File: LICENSE
Requires-Python: >=3.10
Requires-Dist: kubernetes==31.0.0
Requires-Dist: loguru==0.7.3
Requires-Dist: pandas==2.2.3
Requires-Dist: python-dotenv==1.0.1
Requires-Dist: typer==0.16.0
Provides-Extra: test
Requires-Dist: pytest-cov>=4.1.0; extra == 'test'
Requires-Dist: pytest-mock>=3.10.0; extra == 'test'
Requires-Dist: pytest>=7.0; extra == 'test'
